docx2daisy/__init__.py
docx2daisy/daisy_converter.py
docx2daisy-0.2.0.dist-info/LICENSE.md
docx2daisy-0.2.0.dist-info/METADATA
docx2daisy-0.2.0.dist-info/WHEEL
docx2daisy-0.2.0.dist-info/top_level.txt
docx2daisy-0.2.0.dist-info/RECORD
