Metadata-Version: 2.2
Name: docx2daisy
Version: 0.2.0
Summary: A Python library for converting .docx files to DAISY 3 digital books with document preparation checks
Home-page: https://github.com/yourusername/DOCX2DAISY
Author: Your Name
Author-email: your.email@example.com
Classifier: Programming Language :: Python :: 3
Classifier: License :: OSI Approved :: MIT License
Classifier: Operating System :: OS Independent
Requires-Python: >=3.6
License-File: LICENSE.md
Requires-Dist: python-docx>=0.8.11
Dynamic: author
Dynamic: author-email
Dynamic: classifier
Dynamic: description
Dynamic: description-content-type
Dynamic: home-page
Dynamic: requires-dist
Dynamic: requires-python
Dynamic: summary
